ccxt_1_55_84/__init__.py
ccxt_1_55_84/aax.py
ccxt_1_55_84/aofex.py
ccxt_1_55_84/ascendex.py
ccxt_1_55_84/bequant.py
ccxt_1_55_84/bibox.py
ccxt_1_55_84/bigone.py
ccxt_1_55_84/binance.py
ccxt_1_55_84/binancecoinm.py
ccxt_1_55_84/binanceus.py
ccxt_1_55_84/binanceusdm.py
ccxt_1_55_84/bit2c.py
ccxt_1_55_84/bitbank.py
ccxt_1_55_84/bitbay.py
ccxt_1_55_84/bitbns.py
ccxt_1_55_84/bitcoincom.py
ccxt_1_55_84/bitfinex.py
ccxt_1_55_84/bitfinex2.py
ccxt_1_55_84/bitflyer.py
ccxt_1_55_84/bitforex.py
ccxt_1_55_84/bitget.py
ccxt_1_55_84/bithumb.py
ccxt_1_55_84/bitmart.py
ccxt_1_55_84/bitmex.py
ccxt_1_55_84/bitpanda.py
ccxt_1_55_84/bitso.py
ccxt_1_55_84/bitstamp.py
ccxt_1_55_84/bitstamp1.py
ccxt_1_55_84/bittrex.py
ccxt_1_55_84/bitvavo.py
ccxt_1_55_84/bitz.py
ccxt_1_55_84/bl3p.py
ccxt_1_55_84/braziliex.py
ccxt_1_55_84/btcalpha.py
ccxt_1_55_84/btcbox.py
ccxt_1_55_84/btcmarkets.py
ccxt_1_55_84/btctradeua.py
ccxt_1_55_84/btcturk.py
ccxt_1_55_84/buda.py
ccxt_1_55_84/bw.py
ccxt_1_55_84/bybit.py
ccxt_1_55_84/cdax.py
ccxt_1_55_84/cex.py
ccxt_1_55_84/coinbase.py
ccxt_1_55_84/coinbaseprime.py
ccxt_1_55_84/coinbasepro.py
ccxt_1_55_84/coincheck.py
ccxt_1_55_84/coinegg.py
ccxt_1_55_84/coinex.py
ccxt_1_55_84/coinfalcon.py
ccxt_1_55_84/coinfloor.py
ccxt_1_55_84/coinmarketcap.py
ccxt_1_55_84/coinmate.py
ccxt_1_55_84/coinone.py
ccxt_1_55_84/coinspot.py
ccxt_1_55_84/crex24.py
ccxt_1_55_84/currencycom.py
ccxt_1_55_84/delta.py
ccxt_1_55_84/deribit.py
ccxt_1_55_84/digifinex.py
ccxt_1_55_84/eqonex.py
ccxt_1_55_84/equos.py
ccxt_1_55_84/exmo.py
ccxt_1_55_84/exx.py
ccxt_1_55_84/flowbtc.py
ccxt_1_55_84/ftx.py
ccxt_1_55_84/gateio.py
ccxt_1_55_84/gemini.py
ccxt_1_55_84/hbtc.py
ccxt_1_55_84/hitbtc.py
ccxt_1_55_84/hollaex.py
ccxt_1_55_84/huobi.py
ccxt_1_55_84/huobijp.py
ccxt_1_55_84/huobipro.py
ccxt_1_55_84/idex.py
ccxt_1_55_84/independentreserve.py
ccxt_1_55_84/indodax.py
ccxt_1_55_84/itbit.py
ccxt_1_55_84/kraken.py
ccxt_1_55_84/kucoin.py
ccxt_1_55_84/kuna.py
ccxt_1_55_84/latoken.py
ccxt_1_55_84/lbank.py
ccxt_1_55_84-1.55.84.dist-info/LICENSE
ccxt_1_55_84-1.55.84.dist-info/METADATA
ccxt_1_55_84-1.55.84.dist-info/WHEEL
ccxt_1_55_84-1.55.84.dist-info/top_level.txt
ccxt_1_55_84-1.55.84.dist-info/RECORD
